{"0": "react", "1": "Project Scripts and Dependencies", "2": "TypeScript Compiler Configuration", "3": "Cloudflare Deployment Dependencies", "4": "generate-sitemap.js", "5": "include", "6": ".oxlintrc.json", "7": "CategoriesClient.jsx", "8": "NICEVX Home Page", "9": "page.jsx", "10": "Video Card UI Component", "11": "layout.jsx", "12": "Video Player Client Component", "13": "Home Client Component", "14": "Search Results Component", "15": "Eporner API Integration", "16": "Ad Loading Queue Management", "17": "ESLint Configuration", "18": "PWA and Favicon Assets", "19": "page.jsx", "20": "page.jsx", "21": "page.jsx", "22": "AGENTS.md", "23": "next.config.mjs", "24": "scratch.js", "25": "route.js", "26": "seo.js", "27": "vercel.json", "28": "parse_cats.py", "29": "NICEVX Circular Logo", "30": "icons.svg", "31": "Bluesky Icon", "32": "Discord Icon", "33": "Documentation Icon", "34": "GitHub Icon", "35": "Social Icon", "36": "X Icon", "37": "NICEVX Horizontal Logo", "38": "robots.txt", "39": "Hero Section Graphic", "40": "react.svg", "41": "vite.svg"}